README.txt
setup.py
vendapin.py
pyvendapin.egg-info/PKG-INFO
pyvendapin.egg-info/SOURCES.txt
pyvendapin.egg-info/dependency_links.txt
pyvendapin.egg-info/requires.txt
pyvendapin.egg-info/top_level.txt