Metadata-Version: 1.0
Name: pyvendapin
Version: 0.1
Summary: support the Vendapin serial protocol in Python
Home-page: https://github.com/eighthave/pyvendapin
Author: Hans-Christoph Steiner
Author-email: hans@eds.org
License: GPLv3+
Platform: UNKNOWN
Classifier: Intended Audience :: Developers
Classifier: License :: OSI Approved :: GNU General Public License (GPL)
Classifier: Programming Language :: Python :: 2
Classifier: Topic :: Software Development :: Libraries :: Python Modules
Classifier: Topic :: Office/Business :: Financial :: Point-Of-Sale
Classifier: Topic :: System :: Hardware
